{
    "key": "post_type_685d82049f8a5",
    "title": "Social Media Directory",
    "menu_order": 0,
    "active": true,
    "post_type": "s_m_directory",
    "advanced_configuration": true,
    "import_source": "",
    "import_date": "",
    "labels": {
        "name": "Social Media Directory",
        "singular_name": "Social Media Directory Item",
        "menu_name": "SM Directory",
        "all_items": "All Social Media Directory",
        "edit_item": "Edit Social Media Directory Item",
        "view_item": "View Social Media Directory Item",
        "view_items": "View Social Media Directory",
        "add_new_item": "Add New Social Media Directory Item",
        "add_new": "Add New Social Media Directory Item",
        "new_item": "New Social Media Directory Item",
        "parent_item_colon": "Parent Social Media Directory Item:",
        "search_items": "Search Social Media Directory Items",
        "not_found": "No social media directory items found",
        "not_found_in_trash": "No social media directory items found in Trash",
        "archives": "Social Media Directory Item Archives",
        "attributes": "Social Media Directory Item Attributes",
        "featured_image": "",
        "set_featured_image": "",
        "remove_featured_image": "",
        "use_featured_image": "",
        "insert_into_item": "Insert into social media directory item",
        "uploaded_to_this_item": "Uploaded to this social media directory item",
        "filter_items_list": "Filter social media directory list",
        "filter_by_date": "Filter social media directory by date",
        "items_list_navigation": "Social Media Directory list navigation",
        "items_list": "Social Media Directory list",
        "item_published": "Social Media Directory Item published.",
        "item_published_privately": "Social Media Directory Item published privately.",
        "item_reverted_to_draft": "Social Media Directory Item reverted to draft.",
        "item_scheduled": "Social Media Directory Item scheduled.",
        "item_updated": "Social Media Directory Item updated.",
        "item_link": "Social Media Directory Item Link",
        "item_link_description": "A link to a social media directory item."
    },
    "description": "UC Santa Cruz Social Media Directry",
    "public": true,
    "hierarchical": false,
    "exclude_from_search": false,
    "publicly_queryable": true,
    "show_ui": true,
    "show_in_menu": true,
    "admin_menu_parent": "",
    "show_in_admin_bar": true,
    "show_in_nav_menus": true,
    "show_in_rest": true,
    "rest_base": "",
    "rest_namespace": "wp\/v2",
    "rest_controller_class": "WP_REST_Posts_Controller",
    "menu_position": 20,
    "menu_icon": {
        "type": "dashicons",
        "value": "dashicons-share"
    },
    "rename_capabilities": false,
    "singular_capability_name": "post",
    "plural_capability_name": "posts",
    "supports": [
        "title",
        "custom-fields"
    ],
    "taxonomies": "",
    "has_archive": false,
    "has_archive_slug": "",
    "rewrite": {
        "permalink_rewrite": "post_type_key",
        "with_front": "1",
        "feeds": "0",
        "pages": "1"
    },
    "query_var": "post_type_key",
    "query_var_name": "",
    "can_export": true,
    "delete_with_user": false,
    "register_meta_box_cb": "",
    "enter_title_here": "",
    "modified": 1750959300
}
